{
  "project_info": {
    "project_number": "287635886355",
    "project_id": "omega-art-358519",
    "storage_bucket": "omega-art-358519.appspot.com"
  },
  "client": [
    {
      "client_info": {
        "mobilesdk_app_id": "1:287635886355:android:1bddb07dfb635be5184ae6",
        "android_client_info": {
          "package_name": "com.example.login"
        }
      },
      "oauth_client": [
        {
          "client_id": "287635886355-18f3dn0a1vgpu18afmsgcuoser64sbhm.apps.googleusercontent.com",
          "client_type": 1,
          "android_info": {
            "package_name": "com.example.login",
            "certificate_hash": "46cfdd680896fc973fb0d28393ab8ffc611a291e"
          }
        },
        {
          "client_id": "287635886355-ikordq4alrp6ug79bldhi0hgqgsrhu0l.apps.googleusercontent.com",
          "client_type": 3
        }
      ],
      "api_key": [
        {
          "current_key": "AIzaSyBLOXzQ3PBk59buMkJpeaxxkcF-qmp7PR8"
        }
      ],
      "services": {
        "appinvite_service": {
          "other_platform_oauth_client": [
            {
              "client_id": "287635886355-haoi73ha7b0iip06aug5esgpcc4jorsn.apps.googleusercontent.com",
              "client_type": 3
            }
          ]
        }
      }
    }
  ],
  "configuration_version": "1"
}